featurediscovery/__init__.py
featurediscovery/exporter.py
featurediscovery/kernel_search.py
featurediscovery/plotter.py
featurediscovery/search_routines.py
featurediscovery/fitter/__init__.py
featurediscovery/fitter/abstract_fit_quality.py
featurediscovery/fitter/abstract_fitter.py
featurediscovery/fitter/cupy_fitter.py
featurediscovery/fitter/fit_metrics.py
featurediscovery/fitter/sklearn_fitters.py
featurediscovery/fitter/cupy_nn/__init__.py
featurediscovery/fitter/cupy_nn/costs.py
featurediscovery/fitter/cupy_nn/layers.py
featurediscovery/fitter/cupy_nn/models.py
featurediscovery/fitter/cupy_nn/weight_initializer.py
featurediscovery/fitter/cupy_nn/activation_functions/__init__.py
featurediscovery/fitter/cupy_nn/activation_functions/abstract_activation_function.py
featurediscovery/fitter/cupy_nn/activation_functions/activation_functions.py
featurediscovery/kernels/__init__.py
featurediscovery/kernels/abstract_kernel.py
featurediscovery/kernels/duovariate/__init__.py
featurediscovery/kernels/duovariate/abstract_duovariate.py
featurediscovery/kernels/duovariate/duovariate_kernels.py
featurediscovery/kernels/monovariate/__init__.py
featurediscovery/kernels/monovariate/abstract_monovariate.py
featurediscovery/kernels/monovariate/monovariate_kernels.py
featurediscovery/standardizers/__init__.py
featurediscovery/standardizers/abstract_standardizer.py
featurediscovery/standardizers/standardizers.py
featurediscovery/util/__init__.py
featurediscovery/util/exceptions.py
featurediscovery/util/general_utilities.py
featurediscovery-0.1.1.dist-info/LICENSE
featurediscovery-0.1.1.dist-info/METADATA
featurediscovery-0.1.1.dist-info/WHEEL
featurediscovery-0.1.1.dist-info/entry_points.txt
featurediscovery-0.1.1.dist-info/top_level.txt
featurediscovery-0.1.1.dist-info/RECORD
