Metadata-Version: 2.1
Name: featurediscovery
Version: 0.1.1
Summary: Discover hidden predictive qualities of features in your dataset by testing them for linear separability after applying different kernel transformations.
Home-page: https://github.com/Ddasch/Feature_Discovery
Author: Frederik Schadd
Author-email: featurediscovery@outlook.com
License: LGPL v2.1
Platform: UNKNOWN
Classifier: License :: OSI Approved :: GNU Lesser General Public License v2 or later (LGPLv2+)
Classifier: Programming Language :: Python :: 3
Classifier: Programming Language :: Python :: 3.9
Classifier: Environment :: GPU :: NVIDIA CUDA :: 11.5
Classifier: Development Status :: 3 - Alpha
Classifier: Intended Audience :: Developers
Classifier: Intended Audience :: Information Technology
Classifier: Intended Audience :: Science/Research
Classifier: Topic :: Scientific/Engineering :: Artificial Intelligence
Classifier: Topic :: Scientific/Engineering :: Mathematics
License-File: LICENSE
Requires-Dist: pandas (>=1.0.0)
Requires-Dist: scikit-learn (>=1.0.0)
Requires-Dist: cupy-cuda115 (>=9.6.0)
Requires-Dist: matplotlib (>=3.0.0)
Requires-Dist: scipy (>=1.7.0)
